no_cloudflare/__init__.py
no_cloudflare/main.py
no_cloudflare-0.1.2.dist-info/METADATA
no_cloudflare-0.1.2.dist-info/WHEEL
no_cloudflare-0.1.2.dist-info/entry_points.txt
no_cloudflare-0.1.2.dist-info/top_level.txt
no_cloudflare-0.1.2.dist-info/RECORD
