Metadata-Version: 2.1
Name: no-cloudflare
Version: 0.1.2
Requires-Dist: DrissionPage
